registry/__init__.py
py_registry-0.1.2.dist-info/LICENSE.txt
py_registry-0.1.2.dist-info/METADATA
py_registry-0.1.2.dist-info/WHEEL
py_registry-0.1.2.dist-info/top_level.txt
py_registry-0.1.2.dist-info/RECORD
