Metadata-Version: 2.1
Name: py-registry
Version: 0.1.2
Summary: Python Class Registry
Home-page: https://github.com/hbasria/py-registry
Author: Hasan Basri
Author-email: hbasria@gmail.com
License: MIT
Keywords: Python Class Registry
Platform: UNKNOWN
Classifier: Development Status :: 4 - Beta
Classifier: Intended Audience :: Developers
Classifier: License :: OSI Approved :: MIT License
Classifier: Programming Language :: Python
Classifier: Programming Language :: Python :: 2
Classifier: Programming Language :: Python :: 2.7
Classifier: Programming Language :: Python :: 3
Classifier: Programming Language :: Python :: 3.3
Classifier: Programming Language :: Python :: 3.4
Classifier: Topic :: Software Development
Classifier: Topic :: Software Development :: Libraries :: Python Modules
Requires-Dist: py-dictutils (~=0.1)
